tgloader/__init__.py
tgloader/core.py
tgloader/lang.py
tgloader-0.0.1.dist-info/licenses/LICENSE
tgloader-0.0.1.dist-info/METADATA
tgloader-0.0.1.dist-info/WHEEL
tgloader-0.0.1.dist-info/top_level.txt
tgloader-0.0.1.dist-info/RECORD
