Metadata-Version: 2.4
Name: tgloader
Version: 0.0.1
Summary: Telegram media downloader library
Home-page: https://github.com/1SKcode/tgloader
Author: TgLoader
Author-email: ip387525@gmail.com
Classifier: Programming Language :: Python :: 3
Classifier: License :: OSI Approved :: MIT License
Classifier: Operating System :: OS Independent
Requires-Python: >=3.8
License-File: LICENSE
Requires-Dist: telethon~=1.40.0
Requires-Dist: python-dotenv~=1.1.0
Requires-Dist: PyYAML~=6.0.2
Requires-Dist: aiofiles~=24.1.0
Dynamic: author
Dynamic: author-email
Dynamic: classifier
Dynamic: description
Dynamic: description-content-type
Dynamic: home-page
Dynamic: license-file
Dynamic: requires-dist
Dynamic: requires-python
Dynamic: summary
